MANIFEST.in
README.rst
requirements-test.txt
requirements.txt
setup.cfg
setup.py
pyramid_pages/__init__.py
pyramid_pages/assets.py
pyramid_pages/models.py
pyramid_pages/resources.py
pyramid_pages/routes.py
pyramid_pages/security.py
pyramid_pages/views.py
pyramid_pages.egg-info/PKG-INFO
pyramid_pages.egg-info/SOURCES.txt
pyramid_pages.egg-info/dependency_links.txt
pyramid_pages.egg-info/not-zip-safe
pyramid_pages.egg-info/pbr.json
pyramid_pages.egg-info/requires.txt
pyramid_pages.egg-info/top_level.txt
pyramid_pages/static/favicon.ico
pyramid_pages/static/css/__pyramid_pages.css
pyramid_pages/static/css/main.css
pyramid_pages/static/css/content/content.css
pyramid_pages/static/css/gallery/gallery-list.css
pyramid_pages/static/css/gallery/gallery.css
pyramid_pages/static/css/main-menu/main-menu-title.css
pyramid_pages/static/css/main-menu/main-menu.css
pyramid_pages/static/css/main-menu/main-menu_type_right.css
pyramid_pages/static/css/main-menu/main-menu_type_vertical.css
pyramid_pages/static/css/nav/nav.css
pyramid_pages/static/css/page/page-note.css
pyramid_pages/static/css/page/page-title.css
pyramid_pages/static/css/page/page.css
pyramid_pages/static/css/popup/popup.css
pyramid_pages/static/css/popup/content-gallery/content-gallery.css
pyramid_pages/static/css/vendor/font-awesome.min.css
pyramid_pages/static/css/vendor/main.css
pyramid_pages/static/css/vendor/normalize.css
pyramid_pages/static/css/vendor/font-awesome/font-awesome.min.css
pyramid_pages/static/css/vendor/html5-boilerplate/main.css
pyramid_pages/static/css/wrapper/wrapper.css
pyramid_pages/static/img/logo.png
pyramid_pages/static/js/__pyramid_pages.js
pyramid_pages/static/js/main.js
pyramid_pages/static/js/vendor/jquery.min.js
pyramid_pages/static/js/vendor/jquery/jquery.min.js
pyramid_pages/templates/pyramid_pages/breadcrumbs.jinja2
pyramid_pages/templates/pyramid_pages/index.jinja2
pyramid_pages/templates/pyramid_pages/meta.jinja2
pyramid_pages/templates/pyramid_pages/title.jinja2
pyramid_pages/templates/pyramid_pages/menu/flat.jinja2
pyramid_pages/templates/pyramid_pages/menu/mptt.jinja2
pyramid_pages/tests/__init__.py
pyramid_pages/tests/integration_test.py
pyramid_pages/tests/unit_tests.py